pip_prometheus/__init__.py
pip_prometheus-1.2.1.dist-info/LICENSE
pip_prometheus-1.2.1.dist-info/METADATA
pip_prometheus-1.2.1.dist-info/WHEEL
pip_prometheus-1.2.1.dist-info/top_level.txt
pip_prometheus-1.2.1.dist-info/RECORD
